Changelog
LICENSE
MANIFEST
PKG-INFO
README
TODO
ez_setup.py
googlecode-upload.py
rundoc
setup.cfg
setup.py
setup_src.py
tests.py
astrogrid/VOTable.py
astrogrid/__init__.py
astrogrid/applications.py
astrogrid/astrogrid.chm
astrogrid/community.py
astrogrid/cone.py
astrogrid/config.py
astrogrid/configobj.py
astrogrid/decorators.py
astrogrid/feedback.py
astrogrid/helpbrowser.py
astrogrid/myspace.py
astrogrid/plastic.py
astrogrid/registry.py
astrogrid/release.py
astrogrid/sesame.py
astrogrid/siap.py
astrogrid/stap.py
astrogrid/system.py
astrogrid/terminalcontroller.py
astrogrid/thread2.py
astrogrid/threadmethod.py
astrogrid/threadpool.py
astrogrid/utils.py
astrogrid/vospace.py
astrogrid/watcherrors.py
astrogrid/webserver.py
astrogrid.egg-info/PKG-INFO
astrogrid.egg-info/SOURCES.txt
astrogrid.egg-info/dependency_links.txt
astrogrid.egg-info/top_level.txt
astrogrid.egg-info/zip-safe
astrogrid/examples/__init__.py
astrogrid/examples/conesearch_2mass.py
astrogrid/examples/conesearch_iphas.py
astrogrid/examples/conesearch_sdss.py
astrogrid/examples/conesearch_sdss_parallel.py
astrogrid/examples/convert.py
astrogrid/examples/cutouts_sdss.py
astrogrid/examples/iphas_2mass_xmatch.py
astrogrid/examples/objects.txt
astrogrid/examples/sdss_adql.py
astrogrid/examples/sextractor.py
astrogrid/examples/siapsearch.py
astrogrid/examples/siapsearch_broadcast.py
astrogrid/examples/siapsearch_hst.py
astrogrid/examples/siapsearch_local.py
astrogrid/examples/topcat_plastic.py
astrogrid/examples/wsa_gps.py
astrogrid/examples/xmatch.py
astrogrid/examples/xmatch_ukidss_sdss.py
astrogrid/templates/main.kid
doc/api.pdf
doc/cpplone.py
doc/doc.rst
doc/doc2help.py
doc/rundoc
doc/help/PyFontify.py
doc/help/chmox.jpg
doc/help/compilechm.bat
doc/help/conesearch_2mass.py
doc/help/conesearch_iphas.py
doc/help/createchm.py
doc/help/default.css
doc/help/ic5070.jpg
doc/help/ipython.jpg
doc/help/montage_2mass.py
doc/help/py2html.py
doc/help/rst2htm.py
doc/help/sextractor.py
doc/help/siapsearch.py