Metadata-Version: 1.0
Name: astrogrid
Version: 1.0.4
Summary: Python Interface to ACR
Home-page: http://www.astrogrid.org
Author: Eduardo Gonzalez-Solares
Author-email: eglez@ast.cam.ac.uk
License: http://www.astrogrid.org/LICENSE
Platform: Linux
Platform: Solaris
Platform: Mac OS X
Platform: Win
